[
  {
    "id": 0,
    "name": "What Da Ya Have?",
    "image": "assets/images/Food1.png",
    "alt": "project one application",
    "link": "https://badeshiyan.github.io/What-da-ya-have/",
    "link2": "https://github.com/badeshiyan/What-da-ya-have"
  },
  {
    "id": 1,
    "name": "Track Finder App",
    "image": "../../assets/images/Trackfindersnapshot.png",
    "alt": "track finder application",
    "link": "https://polar-castle-76740.herokuapp.com/",
    "link2": "https://github.com/badeshiyan/Track-Finder-App"
  },
  {
    "id": 2,
    "name": "Workout Tracker",
    "image": "../../assets/images/Tracker.gif",
    "alt": "workout tracker application",
    "link": "https://enigmatic-citadel-15539.herokuapp.com/",
    "link2": "https://github.com/badeshiyan/workout-tracker"
  },
  {
    "id": 3,
    "name": "Budget Tracker",
    "image": "../../assets/images/Budget.gif",
    "alt": "workout tracker application",
    "link": "https://guarded-crag-73571.herokuapp.com/",
    "link2": "https://github.com/badeshiyan/budget-tracker"
  },
  {
    "id": 4,
    "name": "Employee Tracker",
    "image": "../../assets/images/Tracker1.gif",
    "alt": "employee tracker application",
    "link": "https://github.com/badeshiyan/employee-tracker"
  },
  {
    "id": 5,
    "name": "Burger Logger",
    "image": "../../assets/images/Burger1.png",
    "alt": "burger logger application",
    "link": "https://infinite-basin-56194.herokuapp.com/",
    "link2": "https://github.com/badeshiyan/burger"
  }
]
